arcanus/__init__.py
arcanus/association.py
arcanus/base.py
arcanus/utils.py
arcanus/materia/README.md
arcanus/materia/__init__.py
arcanus/materia/base.py
arcanus/materia/sqlalchemy/__init__.py
arcanus/materia/sqlalchemy/base.py
arcanus/materia/sqlalchemy/database.py
arcanus/materia/sqlalchemy/result.py
arcanus-0.1.0.dist-info/METADATA
arcanus-0.1.0.dist-info/WHEEL
arcanus-0.1.0.dist-info/licenses/LICENSE
arcanus-0.1.0.dist-info/RECORD
