Metadata-Version: 2.4
Name: arcanus
Version: 0.1.0
Summary: Glue to bind pydantic schemas with various datasources
Project-URL: Homepage, https://github.com/kalynnka/arcanus
Project-URL: Repository, https://github.com/kalynnka/arcanus
Project-URL: Issues, https://github.com/kalynnka/arcanus/issues
Author-email: arcanus <arcanus@example.com>
License: MIT License
License-File: LICENSE
Keywords: database,datasource,orm,pydantic,schema
Classifier: Development Status :: 3 - Alpha
Classifier: Intended Audience :: Developers
Classifier: License :: OSI Approved :: MIT License
Classifier: Operating System :: OS Independent
Classifier: Programming Language :: Python :: 3
Classifier: Programming Language :: Python :: 3.11
Classifier: Programming Language :: Python :: 3.12
Classifier: Topic :: Database
Classifier: Topic :: Software Development :: Libraries :: Python Modules
Requires-Python: >=3.11
Requires-Dist: greenlet>=3.2.4
Requires-Dist: pydantic>=2.11.7
Requires-Dist: sqlalchemy>=2.0.0
Provides-Extra: dev
Requires-Dist: asyncpg>=0.28.0; extra == 'dev'
Requires-Dist: mypy>=1.0.0; extra == 'dev'
Requires-Dist: pre-commit>=3.0.0; extra == 'dev'
Requires-Dist: pytest-asyncio>=0.21.0; extra == 'dev'
Requires-Dist: pytest>=7.0.0; extra == 'dev'
